{
  "openapi": "3.0.4",
  "info": {
    "title": "API",
    "version": "v1"
  },
  "paths": {
    "/Cart/GetCart/{userId}": {
      "get": {
        "tags": [
          "Cart"
        ],
        "parameters": [
          {
            "name": "userId",
            "in": "path",
            "required": true,
            "schema": {
              "type": "integer",
              "format": "int32"
            }
          }
        ],
        "responses": {
          "200": {
            "description": "OK",
            "content": {
              "text/plain": {
                "schema": {
                  "$ref": "#/components/schemas/Order"
                }
              },
              "application/json": {
                "schema": {
                  "$ref": "#/components/schemas/Order"
                }
              },
              "text/json": {
                "schema": {
                  "$ref": "#/components/schemas/Order"
                }
              }
            }
          }
        }
      }
    },
    "/Product/GetAll": {
      "get": {
        "tags": [
          "Product"
        ],
        "responses": {
          "200": {
            "description": "OK"
          }
        }
      }
    },
    "/Product/GetById/{id}": {
      "get": {
        "tags": [
          "Product"
        ],
        "parameters": [
          {
            "name": "id",
            "in": "path",
            "required": true,
            "schema": {
              "type": "integer",
              "format": "int32"
            }
          }
        ],
        "responses": {
          "200": {
            "description": "OK"
          }
        }
      }
    },
    "/Product/Update/{id}": {
      "put": {
        "tags": [
          "Product"
        ],
        "parameters": [
          {
            "name": "id",
            "in": "path",
            "required": true,
            "schema": {
              "type": "integer",
              "format": "int32"
            }
          }
        ],
        "requestBody": {
          "content": {
            "application/json": {
              "schema": {
                "$ref": "#/components/schemas/Product"
              }
            },
            "text/json": {
              "schema": {
                "$ref": "#/components/schemas/Product"
              }
            },
            "application/*+json": {
              "schema": {
                "$ref": "#/components/schemas/Product"
              }
            }
          }
        },
        "responses": {
          "200": {
            "description": "OK"
          }
        }
      }
    },
    "/api/Auth/login": {
      "post": {
        "tags": [
          "Auth"
        ],
        "requestBody": {
          "content": {
            "application/json": {
              "schema": {
                "$ref": "#/components/schemas/LoginRequest"
              }
            },
            "text/json": {
              "schema": {
                "$ref": "#/components/schemas/LoginRequest"
              }
            },
            "application/*+json": {
              "schema": {
                "$ref": "#/components/schemas/LoginRequest"
              }
            }
          }
        },
        "responses": {
          "200": {
            "description": "OK"
          }
        }
      }
    },
    "/api/Auth/register": {
      "post": {
        "tags": [
          "Auth"
        ],
        "requestBody": {
          "content": {
            "application/json": {
              "schema": {
                "$ref": "#/components/schemas/RegisterRequest"
              }
            },
            "text/json": {
              "schema": {
                "$ref": "#/components/schemas/RegisterRequest"
              }
            },
            "application/*+json": {
              "schema": {
                "$ref": "#/components/schemas/RegisterRequest"
              }
            }
          }
        },
        "responses": {
          "200": {
            "description": "OK"
          }
        }
      }
    },
    "/Cart/CreateCart/{userId}": {
      "post": {
        "tags": [
          "Cart"
        ],
        "parameters": [
          {
            "name": "userId",
            "in": "path",
            "required": true,
            "schema": {
              "type": "integer",
              "format": "int32"
            }
          }
        ],
        "responses": {
          "200": {
            "description": "OK",
            "content": {
              "text/plain": {
                "schema": {
                  "$ref": "#/components/schemas/Order"
                }
              },
              "application/json": {
                "schema": {
                  "$ref": "#/components/schemas/Order"
                }
              },
              "text/json": {
                "schema": {
                  "$ref": "#/components/schemas/Order"
                }
              }
            }
          }
        }
      }
    },
    "/Cart/AddOrUpdateCartItem/{cartId}": {
      "post": {
        "tags": [
          "Cart"
        ],
        "parameters": [
          {
            "name": "cartId",
            "in": "path",
            "required": true,
            "schema": {
              "type": "integer",
              "format": "int32"
            }
          }
        ],
        "requestBody": {
          "content": {
            "application/json": {
              "schema": {
                "$ref": "#/components/schemas/CartItemDto"
              }
            },
            "text/json": {
              "schema": {
                "$ref": "#/components/schemas/CartItemDto"
              }
            },
            "application/*+json": {
              "schema": {
                "$ref": "#/components/schemas/CartItemDto"
              }
            }
          }
        },
        "responses": {
          "200": {
            "description": "OK"
          }
        }
      }
    },
    "/Cart/Checkout/{cartId}": {
      "post": {
        "tags": [
          "Cart"
        ],
        "parameters": [
          {
            "name": "cartId",
            "in": "path",
            "required": true,
            "schema": {
              "type": "integer",
              "format": "int32"
            }
          }
        ],
        "requestBody": {
          "content": {
            "application/json": {
              "schema": {
                "$ref": "#/components/schemas/CheckoutDto"
              }
            },
            "text/json": {
              "schema": {
                "$ref": "#/components/schemas/CheckoutDto"
              }
            },
            "application/*+json": {
              "schema": {
                "$ref": "#/components/schemas/CheckoutDto"
              }
            }
          }
        },
        "responses": {
          "200": {
            "description": "OK"
          }
        }
      }
    },
    "/Product/Create": {
      "post": {
        "tags": [
          "Product"
        ],
        "requestBody": {
          "content": {
            "application/json": {
              "schema": {
                "$ref": "#/components/schemas/Product"
              }
            },
            "text/json": {
              "schema": {
                "$ref": "#/components/schemas/Product"
              }
            },
            "application/*+json": {
              "schema": {
                "$ref": "#/components/schemas/Product"
              }
            }
          }
        },
        "responses": {
          "200": {
            "description": "OK"
          }
        }
      }
    },
    "/Cart/{cartId}/item/{designId}": {
      "delete": {
        "tags": [
          "Cart"
        ],
        "parameters": [
          {
            "name": "cartId",
            "in": "path",
            "required": true,
            "schema": {
              "type": "integer",
              "format": "int32"
            }
          },
          {
            "name": "designId",
            "in": "path",
            "required": true,
            "schema": {
              "type": "integer",
              "format": "int32"
            }
          }
        ],
        "responses": {
          "200": {
            "description": "OK"
          }
        }
      }
    },
    "/Product/Delete/{id}": {
      "delete": {
        "tags": [
          "Product"
        ],
        "parameters": [
          {
            "name": "id",
            "in": "path",
            "required": true,
            "schema": {
              "type": "integer",
              "format": "int32"
            }
          }
        ],
        "responses": {
          "200": {
            "description": "OK"
          }
        }
      }
    }
  },
  "components": {
    "schemas": {
      "Accessory": {
        "type": "object",
        "properties": {
          "accessoryId": {
            "type": "integer",
            "format": "int32"
          },
          "accessoryName": {
            "maxLength": 100,
            "type": "string",
            "nullable": true
          },
          "description": {
            "type": "string",
            "nullable": true
          },
          "accessoryImage": {
            "maxLength": 500,
            "type": "string",
            "nullable": true
          },
          "price": {
            "type": "number",
            "format": "double"
          },
          "customDesignAccessories": {
            "type": "array",
            "items": {
              "$ref": "#/components/schemas/CustomDesignAccessory"
            },
            "nullable": true
          }
        },
        "additionalProperties": false
      },
      "CartItemDto": {
        "type": "object",
        "properties": {
          "designId": {
            "type": "integer",
            "format": "int32"
          },
          "quantity": {
            "type": "integer",
            "format": "int32"
          },
          "price": {
            "type": "number",
            "format": "double"
          }
        },
        "additionalProperties": false
      },
      "CheckoutDto": {
        "type": "object",
        "properties": {
          "totalAmount": {
            "type": "number",
            "format": "double"
          }
        },
        "additionalProperties": false
      },
      "CustomDesign": {
        "type": "object",
        "properties": {
          "designId": {
            "type": "integer",
            "format": "int32"
          },
          "userId": {
            "type": "integer",
            "format": "int32",
            "nullable": true
          },
          "user": {
            "$ref": "#/components/schemas/User"
          },
          "baseProductId": {
            "type": "integer",
            "format": "int32",
            "nullable": true
          },
          "baseProduct": {
            "$ref": "#/components/schemas/Product"
          },
          "materialId": {
            "type": "integer",
            "format": "int32",
            "nullable": true
          },
          "material": {
            "$ref": "#/components/schemas/Material"
          },
          "textureId": {
            "type": "integer",
            "format": "int32",
            "nullable": true
          },
          "texture": {
            "$ref": "#/components/schemas/Texture"
          },
          "model3DId": {
            "type": "integer",
            "format": "int32",
            "nullable": true
          },
          "model3D": {
            "$ref": "#/components/schemas/ProductModel"
          },
          "previewImage": {
            "maxLength": 500,
            "type": "string",
            "nullable": true
          },
          "description": {
            "type": "string",
            "nullable": true
          },
          "isPublic": {
            "type": "boolean"
          },
          "createdAt": {
            "type": "string",
            "format": "date-time"
          },
          "customDesignAccessories": {
            "type": "array",
            "items": {
              "$ref": "#/components/schemas/CustomDesignAccessory"
            },
            "nullable": true
          },
          "orderDetails": {
            "type": "array",
            "items": {
              "$ref": "#/components/schemas/OrderDetail"
            },
            "nullable": true
          }
        },
        "additionalProperties": false
      },
      "CustomDesignAccessory": {
        "type": "object",
        "properties": {
          "designId": {
            "type": "integer",
            "format": "int32"
          },
          "design": {
            "$ref": "#/components/schemas/CustomDesign"
          },
          "accessoryId": {
            "type": "integer",
            "format": "int32"
          },
          "accessory": {
            "$ref": "#/components/schemas/Accessory"
          },
          "quantity": {
            "type": "integer",
            "format": "int32"
          }
        },
        "additionalProperties": false
      },
      "LoginRequest": {
        "type": "object",
        "properties": {
          "username": {
            "type": "string",
            "nullable": true
          },
          "password": {
            "type": "string",
            "nullable": true
          }
        },
        "additionalProperties": false
      },
      "Material": {
        "type": "object",
        "properties": {
          "materialId": {
            "type": "integer",
            "format": "int32"
          },
          "materialName": {
            "maxLength": 100,
            "type": "string",
            "nullable": true
          },
          "description": {
            "type": "string",
            "nullable": true
          },
          "colorCode": {
            "maxLength": 20,
            "type": "string",
            "nullable": true
          },
          "customDesigns": {
            "type": "array",
            "items": {
              "$ref": "#/components/schemas/CustomDesign"
            },
            "nullable": true
          }
        },
        "additionalProperties": false
      },
      "Order": {
        "type": "object",
        "properties": {
          "orderId": {
            "type": "integer",
            "format": "int32"
          },
          "userId": {
            "type": "integer",
            "format": "int32",
            "nullable": true
          },
          "user": {
            "$ref": "#/components/schemas/User"
          },
          "orderDate": {
            "type": "string",
            "format": "date-time"
          },
          "totalAmount": {
            "type": "number",
            "format": "double"
          },
          "status": {
            "maxLength": 50,
            "type": "string",
            "nullable": true
          },
          "orderDetails": {
            "type": "array",
            "items": {
              "$ref": "#/components/schemas/OrderDetail"
            },
            "nullable": true
          }
        },
        "additionalProperties": false
      },
      "OrderDetail": {
        "type": "object",
        "properties": {
          "orderDetailId": {
            "type": "integer",
            "format": "int32"
          },
          "orderId": {
            "type": "integer",
            "format": "int32",
            "nullable": true
          },
          "order": {
            "$ref": "#/components/schemas/Order"
          },
          "productId": {
            "type": "integer",
            "format": "int32",
            "nullable": true
          },
          "product": {
            "$ref": "#/components/schemas/Product"
          },
          "designId": {
            "type": "integer",
            "format": "int32",
            "nullable": true
          },
          "design": {
            "$ref": "#/components/schemas/CustomDesign"
          },
          "quantity": {
            "type": "integer",
            "format": "int32"
          },
          "price": {
            "type": "number",
            "format": "double"
          }
        },
        "additionalProperties": false
      },
      "Product": {
        "required": [
          "productName"
        ],
        "type": "object",
        "properties": {
          "productId": {
            "type": "integer",
            "format": "int32"
          },
          "productName": {
            "maxLength": 100,
            "minLength": 1,
            "type": "string"
          },
          "description": {
            "type": "string",
            "nullable": true
          },
          "price": {
            "type": "number",
            "format": "double"
          },
          "previewImage": {
            "maxLength": 500,
            "type": "string",
            "nullable": true
          },
          "model3DId": {
            "type": "integer",
            "format": "int32",
            "nullable": true
          },
          "model3D": {
            "$ref": "#/components/schemas/ProductModel"
          },
          "createdAt": {
            "type": "string",
            "format": "date-time"
          },
          "orderDetails": {
            "type": "array",
            "items": {
              "$ref": "#/components/schemas/OrderDetail"
            },
            "nullable": true
          },
          "customDesigns": {
            "type": "array",
            "items": {
              "$ref": "#/components/schemas/CustomDesign"
            },
            "nullable": true
          }
        },
        "additionalProperties": false
      },
      "ProductModel": {
        "type": "object",
        "properties": {
          "model3DId": {
            "type": "integer",
            "format": "int32"
          },
          "fileName": {
            "maxLength": 255,
            "type": "string",
            "nullable": true
          },
          "filePath": {
            "maxLength": 500,
            "type": "string",
            "nullable": true
          },
          "fileType": {
            "maxLength": 50,
            "type": "string",
            "nullable": true
          },
          "products": {
            "type": "array",
            "items": {
              "$ref": "#/components/schemas/Product"
            },
            "nullable": true
          },
          "customDesigns": {
            "type": "array",
            "items": {
              "$ref": "#/components/schemas/CustomDesign"
            },
            "nullable": true
          }
        },
        "additionalProperties": false
      },
      "RegisterRequest": {
        "type": "object",
        "properties": {
          "fullName": {
            "type": "string",
            "nullable": true
          },
          "password": {
            "type": "string",
            "nullable": true
          },
          "email": {
            "type": "string",
            "nullable": true
          }
        },
        "additionalProperties": false
      },
      "Role": {
        "required": [
          "roleName"
        ],
        "type": "object",
        "properties": {
          "roleId": {
            "type": "integer",
            "format": "int32"
          },
          "roleName": {
            "maxLength": 50,
            "minLength": 1,
            "type": "string"
          },
          "users": {
            "type": "array",
            "items": {
              "$ref": "#/components/schemas/User"
            },
            "nullable": true
          }
        },
        "additionalProperties": false
      },
      "Texture": {
        "type": "object",
        "properties": {
          "textureId": {
            "type": "integer",
            "format": "int32"
          },
          "textureName": {
            "maxLength": 100,
            "type": "string",
            "nullable": true
          },
          "description": {
            "type": "string",
            "nullable": true
          },
          "texturePath": {
            "maxLength": 500,
            "type": "string",
            "nullable": true
          },
          "customDesigns": {
            "type": "array",
            "items": {
              "$ref": "#/components/schemas/CustomDesign"
            },
            "nullable": true
          }
        },
        "additionalProperties": false
      },
      "User": {
        "required": [
          "email",
          "passwordHash"
        ],
        "type": "object",
        "properties": {
          "userId": {
            "type": "integer",
            "format": "int32"
          },
          "fullName": {
            "maxLength": 100,
            "type": "string",
            "nullable": true
          },
          "email": {
            "maxLength": 100,
            "minLength": 1,
            "type": "string"
          },
          "passwordHash": {
            "maxLength": 255,
            "minLength": 1,
            "type": "string"
          },
          "roleId": {
            "type": "integer",
            "format": "int32",
            "nullable": true
          },
          "role": {
            "$ref": "#/components/schemas/Role"
          },
          "createdAt": {
            "type": "string",
            "format": "date-time"
          },
          "orders": {
            "type": "array",
            "items": {
              "$ref": "#/components/schemas/Order"
            },
            "nullable": true
          },
          "customDesigns": {
            "type": "array",
            "items": {
              "$ref": "#/components/schemas/CustomDesign"
            },
            "nullable": true
          }
        },
        "additionalProperties": false
      }
    },
    "securitySchemes": {
      "Bearer": {
        "type": "http",
        "description": "JWT Authorization header sử dụng scheme Bearer.",
        "scheme": "bearer"
      }
    }
  },
  "security": [
    {
      "Bearer": [ ]
    }
  ]
}